{
    "title": "Treia","type": "comune","permalink": "http://dev.albopop.it/comune/treia/","accessible":true,"author":"Alessio Cimarelli \u003calessio.cimarelli@gmail.com\u003e (http://www.ricostruzionetrasparente.it)","draft":false,"facebook":null,"image":"c_l366.png","ipa":"c_l366","iscjklanguage":false,"istat":17964,"lat":43.311369,"lng":13.313053,"official":false,"original":"http://www.comune.treia.mc.it/albo-pretorio/","pdf":null,"provincia":"Macerata","regione":"Marche","repo":"https://github.com/RicostruzioneTrasparente/rt-scrapers/","rss":"http://feeds.ricostruzionetrasparente.it/albi_pretori/Treia_feed.xml","standard":true,"tags":["rt"],"telegram":null,"title":"Treia","twitter":null
}