{
    "title": "Caldarola","type": "comune","permalink": "http://dev.albopop.it/comune/caldarola/","accessible":true,"author":"Alessio Cimarelli \u003calessio.cimarelli@gmail.com\u003e (http://www.ricostruzionetrasparente.it)","draft":false,"facebook":null,"image":"c_b398.png","ipa":"c_b398","iscjklanguage":false,"istat":17926,"lat":43.138169,"lng":13.225139,"official":false,"original":"http://www.comune.caldarola.mc.it/albo-pretorio/","pdf":null,"provincia":"Macerata","regione":"Marche","repo":"https://github.com/RicostruzioneTrasparente/rt-scrapers/","rss":"http://feeds.ricostruzionetrasparente.it/albi_pretori/Caldarola_feed.xml","standard":true,"tags":["rt"],"telegram":null,"title":"Caldarola","twitter":null
}