{
    "title": "Rieti","type": "comune","permalink": "http://dev.albopop.it/comune/rieti/","accessible":true,"author":"SemplicePA \u003cinfo@eti3.it\u003e (http://www.semplicepa.it)","draft":false,"facebook":null,"image":"c_h282.png","ipa":"c_h282","iscjklanguage":false,"istat":57059,"lat":42.40443,"lng":12.856702,"official":false,"original":"http://albopretorio.insielmercato.it/AlboRieti/home.html","pdf":null,"provincia":"Rieti","regione":"Lazio","repo":null,"rss":"http://www.semplicepa.it/rssfeed/057059.xml","standard":true,"tags":["tci","rt"],"telegram":null,"title":"Rieti","twitter":null
}