{
    "title": "Manduria","type": "comune","permalink": "http://dev.albopop.it/comune/manduria/","accessible":true,"author":["@Vic39 (http://vincentforty.weebly.com/)","Cooperativa Sociale Lacanosa (http://www.cooperativasociale.com/)"],"draft":false,"facebook":null,"image":"c_e882.png","ipa":"c_e882","iscjklanguage":false,"istat":30218,"lat":40.402778,"lng":17.634167,"official":false,"original":"http://www.comune.manduria.ta.it/albo-pretorio","pdf":null,"provincia":"Taranto","regione":"Puglia","repo":null,"rss":"http://feeds.feedburner.com/AlbopopManduria","standard":false,"tags":[],"telegram":"https://telegram.me/albopopmanduriata","title":"Manduria","twitter":null
}